image_shuffler/__init__.py
image_shuffler/shuffler.py
image_shuffler-1.0.2.dist-info/LICENSE
image_shuffler-1.0.2.dist-info/METADATA
image_shuffler-1.0.2.dist-info/WHEEL
image_shuffler-1.0.2.dist-info/top_level.txt
image_shuffler-1.0.2.dist-info/RECORD
