Metadata-Version: 2.1
Name: image-shuffler
Version: 1.0.2
Summary: Split an image into n-pieces and shuffle it.
Home-page: https://github.com/gabrielstork/image-shuffler
Author: Gabriel Stork
Author-email: storkdeveloper@gmail.com
License: MIT
Keywords: image shuffler slicer picture pieces
Platform: UNKNOWN
Classifier: Development Status :: 5 - Production/Stable
Classifier: Programming Language :: Python :: 3
Classifier: License :: OSI Approved :: MIT License
Classifier: Operating System :: OS Independent
Requires-Python: >=3
License-File: LICENSE
Requires-Dist: numpy
Requires-Dist: opencv-python
